mopac_step/__init__.py
mopac_step/__main__.py
mopac_step/_version.py
mopac_step/energy.py
mopac_step/energy_parameters.py
mopac_step/energy_step.py
mopac_step/forceconstants.py
mopac_step/forceconstants_parameters.py
mopac_step/forceconstants_step.py
mopac_step/installer.py
mopac_step/ir.py
mopac_step/ir_parameters.py
mopac_step/ir_step.py
mopac_step/lewis_structure.py
mopac_step/lewis_structure_parameters.py
mopac_step/lewis_structure_step.py
mopac_step/metadata.py
mopac_step/mopac.py
mopac_step/mopac_base.py
mopac_step/mopac_step.py
mopac_step/optimization.py
mopac_step/optimization_parameters.py
mopac_step/optimization_step.py
mopac_step/thermodynamics.py
mopac_step/thermodynamics_parameters.py
mopac_step/thermodynamics_step.py
mopac_step/tk_energy.py
mopac_step/tk_forceconstants.py
mopac_step/tk_ir.py
mopac_step/tk_lewis_structure.py
mopac_step/tk_mopac.py
mopac_step/tk_optimization.py
mopac_step/tk_thermodynamics.py
mopac_step/data/configuration.txt
mopac_step/data/mopac.ini
mopac_step/data/properties.csv
mopac_step/data/references.bib
mopac_step/data/seamm-mopac.yml
mopac_step-2025.12.21.dist-info/licenses/AUTHORS.rst
mopac_step-2025.12.21.dist-info/licenses/LICENSE
mopac_step-2025.12.21.dist-info/METADATA
mopac_step-2025.12.21.dist-info/WHEEL
mopac_step-2025.12.21.dist-info/entry_points.txt
mopac_step-2025.12.21.dist-info/top_level.txt
mopac_step-2025.12.21.dist-info/zip-safe
mopac_step-2025.12.21.dist-info/RECORD
